Metadata-Version: 2.1
Name: odoo14-addon-ddmrp
Version: 14.0.1.24.0
Summary: Demand Driven Material Requirements Planning
Home-page: https://github.com/OCA/ddmrp
Author: ForgeFlow, Odoo Community Association (OCA)
Author-email: support@odoo-community.org
License: LGPL-3
Platform: UNKNOWN
Classifier: Programming Language :: Python
Classifier: Framework :: Odoo
Classifier: Framework :: Odoo :: 14.0
Classifier: License :: OSI Approved :: GNU Lesser General Public License v3 (LGPLv3)
Classifier: Development Status :: 4 - Beta
Requires-Python: >=3.6
Requires-Dist: odoo14-addon-base-cron-exclusion
Requires-Dist: odoo14-addon-mrp-multi-level
Requires-Dist: odoo14-addon-stock-demand-estimate
Requires-Dist: odoo14-addon-stock-helper
Requires-Dist: odoo14-addon-stock-warehouse-calendar
Requires-Dist: odoo14-addon-web-widget-bokeh-chart
Requires-Dist: odoo <14.1dev,>=14.0a
